<?xml version="1.0" encoding="UTF-8"?>
<objects serializationModel="Studio.02.02.00">
	<object class="AudioFile" id="{e51f3b29-cc4d-4f86-bc53-150c007cdb14}">
		<property name="assetPath">
			<value>7drink.wav</value>
		</property>
		<property name="frequencyInKHz">
			<value>48</value>
		</property>
		<property name="channelCount">
			<value>2</value>
		</property>
		<property name="length">
			<value>0.7270416666666667</value>
		</property>
		<relationship name="masterAssetFolder">
			<destination>{e917ee22-dc14-412b-810f-86972287131e}</destination>
		</relationship>
	</object>
</objects>
